relign/__init__.py
relign/config.py
relign/curriculum.py
relign/generator.py
relign/helpers.py
relign/network.py
relign/noise.py
relign/save_model.py
relign/algorithms/__init__.py
relign/algorithms/baseline_algorithms.py
relign/algorithms/coordinate_walk.py
relign/algorithms/forest.py
relign/algorithms/gp.py
relign/algorithms/random_search.py
relign/algorithms/scan.py
relign/algorithms/trust_ncg.py
relign/data/GaussianIntensityEnv/gt__50x50.npy
relign/data/LensEnv/config.txt
relign/data/LensEnv/gt__spec_l2__ref_pattern_rectangle__sample_count_65536__50x50.npy
relign/data/LensEnv/gt__spec_l2__ref_pattern_siemens__sample_count_65536__50x50.npy
relign/data/LensEnv/gt__spec_l3__ref_pattern_rectangle__sample_count_65536__50x50.npy
relign/data/LensEnv/gt__spec_l3__ref_pattern_siemens__sample_count_65536__50x50.npy
relign/data/LensEnv/gt__spec_od__ref_pattern_bmw__sample_count_65536__200x200.npy
relign/data/LensEnv/gt__spec_od__ref_pattern_rectangle__sample_count_65536__50x50.npy
relign/data/LensEnv/gt__spec_od__ref_pattern_siemens__sample_count_65536__200x200.npy
relign/data/LensEnv/gt__spec_od__ref_pattern_siemens__sample_count_65536__50x50.npy
relign/data/LensEnv/lens.PLY
relign/data/LensEnv/lens_0.PLY
relign/data/LensEnv/lens_1.PLY
relign/data/LensEnv/lens_2.PLY
relign/data/LensEnv/lens_3.PLY
relign/data/LensEnv/lens_mount.PLY
relign/data/LensEnv/stop_0.PLY
relign/data/LensEnv/stop_1.PLY
relign/data/LensEnv/high_res/lens_0.PLY
relign/data/LensEnv/high_res/lens_1.PLY
relign/data/LensEnv/high_res/lens_2.PLY
relign/data/LensEnv/high_res/lens_3.PLY
relign/data/LensEnv/high_res/lens_mount.PLY
relign/data/LensEnv/high_res/stop_0.PLY
relign/data/LensEnv/high_res/stop_1.PLY
relign/data/ref_patterns/bmw.png
relign/data/ref_patterns/chessboards.png
relign/data/ref_patterns/rectangle.png
relign/data/ref_patterns/siemens.png
relign/data/ref_patterns/usaf.png
relign-0.1.0.dist-info/licenses/LICENSE
relign-0.1.0.dist-info/METADATA
relign-0.1.0.dist-info/WHEEL
relign-0.1.0.dist-info/top_level.txt
relign-0.1.0.dist-info/RECORD
